gwdcli/__init__.py
gwdcli/__main__.py
gwdcli/csv/__init__.py
gwdcli/csv/__main__.py
gwdcli/csv/egauge_download.py
gwdcli/csv/settings.py
gwdcli/events/__init__.py
gwdcli/events/__main__.py
gwdcli/events/models.py
gwdcli/events/mqtt.py
gwdcli/events/queue_loop.py
gwdcli/events/settings.py
gwdcli/events/show_dir.py
gwdcli/events/sync.py
gwdcli/events/tui.py
gwdcli/py.typed
gwdcli/utils/__init__.py
gwdcli/utils/settings.py
gridworks_debug_cli-0.3.2.dist-info/LICENSE
gridworks_debug_cli-0.3.2.dist-info/METADATA
gridworks_debug_cli-0.3.2.dist-info/WHEEL
gridworks_debug_cli-0.3.2.dist-info/entry_points.txt
gridworks_debug_cli-0.3.2.dist-info/RECORD
