Metadata-Version: 2.1
Name: gridworks-debug-cli
Version: 0.3.2
Summary: Gridworks Debug Cli
Home-page: https://github.com/anschweitzer/gridworks-debug-cli
License: MIT
Author: Andrew Schweitzer
Author-email: schweitz72@gmail.com
Requires-Python: >=3.11,<4.0
Classifier: Development Status :: 3 - Alpha
Classifier: License :: OSI Approved :: MIT License
Classifier: Programming Language :: Python :: 3
Classifier: Programming Language :: Python :: 3.11
Classifier: Programming Language :: Python :: 3.12
Classifier: Programming Language :: Python :: 3.13
Requires-Dist: aiobotocore (>=2.4.2,<3.0.0)
Requires-Dist: aiomqtt (>=2.0.1,<3.0.0)
Requires-Dist: anyio (>=3.6.2,<4.0.0)
Requires-Dist: click (>=8.0.1)
Requires-Dist: gridworks-protocol (>=1.2.1,<2.0.0)
Requires-Dist: pandas (>=2.2.3,<3.0.0)
Requires-Dist: pendulum (>=3.0.0,<4.0.0)
Requires-Dist: pydantic (>=2,<3)
Requires-Dist: pydantic-settings (>=2.7.1,<3.0.0)
Requires-Dist: pytimeparse2 (>=1.6.0,<2.0.0)
Requires-Dist: result (>=0.9.0,<0.10.0)
Requires-Dist: rich (>=13.2.0,<14.0.0)
Requires-Dist: typer (>=0.7.0,<0.8.0)
Requires-Dist: types-aiobotocore[essential] (>=2.4.2,<3.0.0)
Requires-Dist: xdg (>=5.1.1,<6.0.0)
Requires-Dist: yarl (>=1.8.2,<2.0.0)
Project-URL: Changelog, https://github.com/anschweitzer/gridworks-debug-cli/releases
Project-URL: Documentation, https://gridworks-debug-cli.readthedocs.io
Project-URL: Repository, https://github.com/anschweitzer/gridworks-debug-cli
